socket_jsonrpc/__init__.py
socket_jsonrpc/py.typed
socket_jsonrpc-0.0.0.dist-info/METADATA
socket_jsonrpc-0.0.0.dist-info/WHEEL
socket_jsonrpc-0.0.0.dist-info/licenses/LICENSE
socket_jsonrpc-0.0.0.dist-info/RECORD
